{
  "Sport TV1.pt": {
    "url": "https://tcxoov.6670391863.store:8443/hls/xt4p2tyjgzsp4t.m3u8?s=ABlz_8zPE7DOkpk-jav1mQ&e=1756504985",
    "expires_at": 1756504955
  },
  "Sport TV2.pt": {
    "url": "https://tcxoov.6670391863.store:8443/hls/dm4f0c0bxcxxsau.m3u8?s=uizgpS4gtBD3PwGWEohK0w&e=1756505007",
    "expires_at": 1756504977
  },
  "Sport TV3.pt": {
    "url": "https://tcxoov.6670391863.store:8443/hls/4h80gffrr5803z.m3u8?s=bpgfS73dhGsEw8jyE_FXGQ&e=1756505029",
    "expires_at": 1756504999
  },
  "Sport TV4.pt": {
    "url": "https://tcxoov.6670391863.store:8443/hls/hqwwgwycxiiy.m3u8?s=V4phg9ivWfA6lfhu0S3kxw&e=1756505051",
    "expires_at": 1756505021
  },
  "Sport TV5.pt": {
    "url": "https://tcxoov.6670391863.store:8443/hls/vndxx07b0.m3u8?s=c22FBY_adaf_Sq9oLJg0XA&e=1756505072",
    "expires_at": 1756505042
  },
  "DAZN 1.pt": {
    "url": "https://tcxoov.6670391863.store:8443/hls/cytjtehz5yzmrt.m3u8?s=yO2ThjVYlHoDnEY85j7-Mw&e=1756505094",
    "expires_at": 1756505064
  },
  "DAZN 2.pt": {
    "url": "https://tcxoov.6670391863.store:8443/hls/98n38s9qy27ra.m3u8?s=_x3hKOscb11wVXpybadfRA&e=1756505116",
    "expires_at": 1756505086
  }
}